physioblocks/__init__.py
physioblocks/base/__init__.py
physioblocks/base/operators.py
physioblocks/base/registers.py
physioblocks/computing/__init__.py
physioblocks/computing/assembling.py
physioblocks/computing/models.py
physioblocks/computing/quantities.py
physioblocks/configuration/__init__.py
physioblocks/configuration/aliases.py
physioblocks/configuration/base.py
physioblocks/configuration/constants.py
physioblocks/configuration/functions.py
physioblocks/configuration/computing/__init__.py
physioblocks/configuration/computing/quantities.py
physioblocks/configuration/description/__init__.py
physioblocks/configuration/description/blocks.py
physioblocks/configuration/description/nets.py
physioblocks/configuration/simulation/__init__.py
physioblocks/configuration/simulation/simulations.py
physioblocks/description/__init__.py
physioblocks/description/blocks.py
physioblocks/description/flux.py
physioblocks/description/nets.py
physioblocks/io/__init__.py
physioblocks/io/aliases.py
physioblocks/io/configuration.py
physioblocks/launcher/__main__.py
physioblocks/launcher/configuration.py
physioblocks/launcher/constants.py
physioblocks/launcher/files.py
physioblocks/launcher/series.py
physioblocks/launcher/configure/__main__.py
physioblocks/library/__init__.py
physioblocks/library/aliases/blocks/c_block.json
physioblocks/library/aliases/blocks/rc_block.json
physioblocks/library/aliases/blocks/rcr_block.json
physioblocks/library/aliases/blocks/spherical_cavity_block.json
physioblocks/library/aliases/blocks/valve_rl_block.json
physioblocks/library/aliases/flux/heart_flux_dof_couples.jsonc
physioblocks/library/aliases/model_components/active_law_macro_huxley_two_moments.json
physioblocks/library/aliases/model_components/rheology_fiber_additive.json
physioblocks/library/aliases/model_components/spherical_dynamics.json
physioblocks/library/aliases/model_components/velocity_law_hht.json
physioblocks/library/aliases/nets/circulation_alone_net.json
physioblocks-1.0.1.dist-info/METADATA
physioblocks-1.0.1.dist-info/WHEEL
physioblocks-1.0.1.dist-info/licenses/licenses/GPL-3.0-only.txt
physioblocks-1.0.1.dist-info/licenses/licenses/LGPL-3.0-only.txt
physioblocks-1.0.1.dist-info/RECORD
