Metadata-Version: 2.4
Name: physioblocks
Version: 1.0.1
Dynamic: Author
Dynamic: Author-email
Dynamic: License
Dynamic: License-Expression
Summary: Physioblocks allows the simulation of dynamical models of physiological systems
Project-URL: Homepage, https://github.com/physioblocks/physioblocks
Project-URL: Documentation, https://physioblocks.gitlabpages.inria.fr/physioblocks/
Project-URL: Issues, https://github.com/physioblocks/physioblocks/issues
Project-URL: Discussions, https://github.com/physioblocks/physioblocks/discussions
License-File: licenses/GPL-3.0-only.txt
License-File: licenses/LGPL-3.0-only.txt
Keywords: block diagram,cardiovascular modeling,dynamical systems,physiology
Classifier: Development Status :: 5 - Production/Stable
Classifier: Intended Audience :: Science/Research
Classifier: License :: OSI Approved :: GNU Lesser General Public License v3 (LGPLv3)
Classifier: Operating System :: OS Independent
Classifier: Programming Language :: Python :: 3
Classifier: Programming Language :: Python :: 3.10
Classifier: Programming Language :: Python :: 3.11
Classifier: Programming Language :: Python :: 3.12
Classifier: Programming Language :: Python :: 3.13
Classifier: Programming Language :: Python :: 3.14
Classifier: Topic :: Scientific/Engineering :: Mathematics
Classifier: Topic :: Scientific/Engineering :: Medical Science Apps.
Requires-Python: >=3.10
Requires-Dist: numpy
Requires-Dist: pandas
Requires-Dist: plotly
Requires-Dist: pyarrow
Requires-Dist: regex
Requires-Dist: scipy
Provides-Extra: doc
Requires-Dist: sphinx; extra == 'doc'
Requires-Dist: sphinx-rtd-theme; extra == 'doc'
Requires-Dist: sphinxcontrib-tikz; extra == 'doc'
Provides-Extra: quality
Requires-Dist: mypy; extra == 'quality'
Requires-Dist: ruff; extra == 'quality'
Provides-Extra: test
Requires-Dist: coverage; extra == 'test'
Requires-Dist: pytest>=8; extra == 'test'
Provides-Extra: tox
Requires-Dist: tox>=4; extra == 'tox'
